mnist/__init__.py
mnist/mnist.py
mnist_py-0.5.dist-info/METADATA
mnist_py-0.5.dist-info/WHEEL
mnist_py-0.5.dist-info/top_level.txt
mnist_py-0.5.dist-info/RECORD
