Metadata-Version: 2.1
Name: mnist-py
Version: 0.5
Summary: Lighweight Numpy MNIST loader
Home-page: https://github.com/mattpetersen/mnist-py
Author: Matt Petersen
Author-email: peterm0273@gmail.com
License: MIT
Keywords: mnist
Platform: UNKNOWN
Classifier: Programming Language :: Python :: 3
Classifier: License :: OSI Approved :: MIT License
Classifier: Operating System :: OS Independent
Requires-Dist: numpy
Requires-Dist: requests
